README
setup.py
kumaresh_package.egg-info/PKG-INFO
kumaresh_package.egg-info/SOURCES.txt
kumaresh_package.egg-info/dependency_links.txt
kumaresh_package.egg-info/requires.txt
kumaresh_package.egg-info/top_level.txt
src/__init__.py
src/kumaresh.py