Metadata-Version: 1.1
Name: kumaresh-package
Version: 1.0.0
Summary: Kumaresh project
Home-page: UNKNOWN
Author: Kumaresh Visakan Murugan
Author-email: UNKNOWN
License: MIT
Keywords: kumaresh
Platform: UNKNOWN
Classifier: Programming Language :: Python :: 2.7
Classifier: Development Status :: 4 - Beta
Classifier: Intended Audience :: Science/Research
Classifier: License :: OSI Approved :: MIT License
Classifier: Operating System :: OS Independent
Classifier: Topic :: Scientific/Engineering :: Information Analysis
Classifier: Topic :: Scientific/Engineering :: Physics
Classifier: Topic :: Scientific/Engineering :: Chemistry
Classifier: Topic :: Software Development :: Libraries :: Python Modules
